data/TAMU Classes/Spring 2024/ECEN350/Lab7/ALU.v
`define AND   4'b0000
`define OR    4'b0001
`define ADD   4'b0010
`define SUB   4'b0110
`define PassB 4'b0111

module ALU(BusW, BusA, BusB, ALUCtrl, Zero);
    
    output  [63:0] BusW;
    input   [63:0] BusA, BusB;
    input   [3:0] ALUCtrl;
    output  Zero;
    reg     [63:0] BusW;
    
    always @(ALUCtrl or BusA or BusB) begin //go to each case which is specified
        case(ALUCtrl)
        `AND: begin
            BusW = BusA & BusB;
        end
	    `OR: begin 
		    BusW = BusA | BusB;
        end
	    `ADD: begin 
		    BusW = BusA + BusB;
        end
	    `SUB: begin 
		    BusW = BusA - BusB;
        end
	    `PassB: begin 
		    BusW = BusB;
        end
        endcase
    end

    assign Zero = (BusW == 0) ? 1'b1 : 1'b0;
endmodule

data/TAMU Classes/Spring 2024/ECEN350/Lab7/ALUTest.v
`timescale 1ns / 1ps


`define STRLEN 15
module ALUTest;
	initial begin
		$dumpfile("ALUTest.vcd");
		$dumpvars(0, ALUTest);
	end
	task passTest;
		input [63:0] actualOut, expectedOut;
		input [`STRLEN*8:0] testType;
		inout [7:0] passed;
	
		if(actualOut == expectedOut) begin $display ("%s passed", testType); passed = passed + 1; end
		else $display ("%s failed: %d should be %d", testType, actualOut, expectedOut);
	endtask
	
	task allPassed;
		input [14:0] passed;
		input [14:0] numTests;
		
		if(passed == numTests) $display ("All tests passed");
		else $display("Some tests failed");
	endtask
	
	// Inputs
    reg [63:0] BusA, BusB;
    reg [3:0] ALUCtrl;
    reg [14:0] passed;

	// Outputs
    wire [63:0] BusW;
    wire Zero;

	// Instantiate the Unit Under Test (UUT)
    ALU uut (
        .BusW(BusW), 
        .BusA(BusA), 
        .BusB(BusB), 
        .ALUCtrl(ALUCtrl), 
        .Zero(Zero)
    );

	initial begin
		// Initialize Inputs
		BusA = 0;
		BusB = 0;
        ALUCtrl = 0;
        passed = 0;

		// Add stimulus here
        //AND
        #90; BusA = 64'b1; BusB = 64'b0; ALUCtrl = `AND; #10; passTest(BusW, 64'b0, "AND Test 1", passed);
        #90; BusA = 64'b1; BusB = 64'b1; ALUCtrl = `AND; #10; passTest(BusW, 64'b1, "AND Test 2", passed);
        #90; BusA = 64'b0; BusB = 64'b1; ALUCtrl = `AND; #10; passTest(BusW, 64'b0, "AND Test 3", passed);

        //OR
        #90; BusA = 64'b0; BusB = 64'b1; ALUCtrl = `OR; #10; passTest(BusW, 64'b1, "OR Test 4", passed);
        #90; BusA = 64'b1; BusB = 64'b1; ALUCtrl = `OR; #10; passTest(BusW, 64'b1, "OR Test 5", passed);
        #90; BusA = 64'b1; BusB = 64'b0; ALUCtrl = `OR; #10; passTest(BusW, 64'b1, "OR Test 6", passed);

        //ADD
        #90; BusA = 64'd10; BusB = 64'd20; ALUCtrl = `ADD; #10; passTest(BusW, 64'd30, "ADD Test 7", passed);
        #90; BusA = 64'd15; BusB = 64'd3; ALUCtrl = `ADD; #10; passTest(BusW, 64'd18, "ADD Test 8", passed);
        #90; BusA = 64'd34; BusB = 64'd43; ALUCtrl = `ADD; #10; passTest(BusW, 64'd77, "ADD Test 9", passed);

        //SUB
        #90; BusA = 64'd50; BusB = 64'd20; ALUCtrl = `SUB; #10; passTest(BusW, 64'd30, "SUB Test 10", passed);
        #90; BusA = 64'd400; BusB = 64'd200; ALUCtrl = `SUB; #10; passTest(BusW, 64'd200, "SUB Test 11", passed);
        #90; BusA = 64'd9; BusB = 64'd3; ALUCtrl = `SUB; #10; passTest(BusW, 64'd6, "SUB Test 12", passed);

        //PassB
        #90; BusA = 64'd0; BusB = 64'd123; ALUCtrl = `PassB; #10; passTest(BusW, 64'd123, "PassB Test 13", passed);
        #90; BusA = 64'd0; BusB = 64'd400; ALUCtrl = `PassB; #10; passTest(BusW, 64'd400, "PassB Test 14", passed);
        #90; BusA = 64'd0; BusB = 64'd200; ALUCtrl = `PassB; #10; passTest(BusW, 64'd200, "PassB Test 15", passed);

		allPassed(passed, 15);

        //15 total test

	end
      
endmodule

data/TAMU Classes/Spring 2024/ECEN350/Lab7/ALUTest.vcd
$date
	Fri Apr  5 15:48:19 2024
$end
$version
	Icarus Verilog
$end
$timescale
	1ps
$end
$scope module ALUTest $end
$var wire 1 ! Zero $end
$var wire 64 " BusW [63:0] $end
$var reg 4 # ALUCtrl [3:0] $end
$var reg 64 $ BusA [63:0] $end
$var reg 64 % BusB [63:0] $end
$var reg 15 & passed [14:0] $end
$scope module uut $end
$var wire 4 ' ALUCtrl [3:0] $end
$var wire 64 ( BusA [63:0] $end
$var wire 64 ) BusB [63:0] $end
$var wire 1 ! Zero $end
$var reg 64 * BusW [63:0] $end
$upscope $end
$scope task allPassed $end
$var reg 15 + numTests [14:0] $end
$var reg 15 , passed [14:0] $end
$upscope $end
$scope task passTest $end
$var reg 64 - actualOut [63:0] $end
$var reg 64 . expectedOut [63:0] $end
$var reg 8 / passed [7:0] $end
$var reg 121 0 testType [120:0] $end
$upscope $end
$upscope $end
$enddefinitions $end
$comment Show the parameter values. $end
$dumpall
$end
#0
$dumpvars
bx 0
bx /
bx .
bx -
bx ,
bx +
b0 *
b0 )
b0 (
b0 '
b0 &
b0 %
b0 $
b0 #
b0 "
1!
$end
#90000
b1 $
b1 (
#100000
b1 &
b1 /
b1000001010011100100010000100000010101000110010101110011011101000010000000110001 0
b0 .
b0 -
#190000
0!
b1 "
b1 *
b1 %
b1 )
#200000
b10 &
b10 /
b1000001010011100100010000100000010101000110010101110011011101000010000000110010 0
b1 .
b1 -
#290000
1!
b0 "
b0 *
b0 $
b0 (
#300000
b11 &
b11 /
b1000001010011100100010000100000010101000110010101110011011101000010000000110011 0
b0 .
b0 -
#390000
0!
b1 "
b1 *
b1 #
b1 '
#400000
b100 &
b100 /
b10011110101001000100000010101000110010101110011011101000010000000110100 0
b1 .
b1 -
#490000
b1 $
b1 (
#500000
b101 &
b101 /
b10011110101001000100000010101000110010101110011011101000010000000110101 0
#590000
b0 %
b0 )
#600000
b110 &
b110 /
b10011110101001000100000010101000110010101110011011101000010000000110110 0
#690000
b11110 "
b11110 *
b10 #
b10 '
b10100 %
b10100 )
b1010 $
b1010 (
#700000
b111 &
b111 /
b1000001010001000100010000100000010101000110010101110011011101000010000000110111 0
b11110 .
b11110 -
#790000
b10010 "
b10010 *
b11 %
b11 )
b1111 $
b1111 (
#800000
b1000 &
b1000 /
b1000001010001000100010000100000010101000110010101110011011101000010000000111000 0
b10010 .
b10010 -
#890000
b1001101 "
b1001101 *
b101011 %
b101011 )
b100010 $
b100010 (
#900000
b1001 &
b1001 /
b1000001010001000100010000100000010101000110010101110011011101000010000000111001 0
b1001101 .
b1001101 -
#990000
b11110 "
b11110 *
b110 #
b110 '
b10100 %
b10100 )
b110010 $
b110010 (
#1000000
b1010 &
b1010 /
b101001101010101010000100010000001010100011001010111001101110100001000000011000100110000 0
b11110 .
b11110 -
#1090000
b11001000 "
b11001000 *
b11001000 %
b11001000 )
b110010000 $
b110010000 (
#1100000
b1011 &
b1011 /
b101001101010101010000100010000001010100011001010111001101110100001000000011000100110001 0
b11001000 .
b11001000 -
#1190000
b110 "
b110 *
b11 %
b11 )
b1001 $
b1001 (
#1200000
b1100 &
b1100 /
b101001101010101010000100010000001010100011001010111001101110100001000000011000100110010 0
b110 .
b110 -
#1290000
b1111011 "
b1111011 *
b111 #
b111 '
b1111011 %
b1111011 )
b0 $
b0 (
#1300000
b1101 &
b1101 /
b1010000011000010111001101110011010000100010000001010100011001010111001101110100001000000011000100110011 0
b1111011 .
b1111011 -
#1390000
b110010000 "
b110010000 *
b110010000 %
b110010000 )
#1400000
b1110 &
b1110 /
b1010000011000010111001101110011010000100010000001010100011001010111001101110100001000000011000100110100 0
b110010000 .
b110010000 -
#1490000
b11001000 "
b11001000 *
b11001000 %
b11001000 )
#1500000
b1111 +
b1111 ,
b1111 &
b1111 /
b1010000011000010111001101110011010000100010000001010100011001010111001101110100001000000011000100110101 0
b11001000 .
b11001000 -
