data/TAMU Classes/Spring 2024/ECEN350/Lab09/NextPClogic.v
//`timescale 1ns / 1ps

module NextPClogic(NextPC, CurrentPC, SignExtImm64, Branch, ALUZero, Uncondbranch); 
   input [63:0] CurrentPC, SignExtImm64; 
   input 	Branch, ALUZero, Uncondbranch; 
   output reg [63:0] NextPC; 

   /* write your code here */ 

    //calculating NextPC based on the condition of the Branch, Unconditional Branch and ALUZero
    always @(*) begin
        //Check if a conditional branch should be taken (branch and ALUZero are true) or if its an unconditional branch
        if ((Branch && ALUZero) || Uncondbranch) begin //If unconditional, branch regardless of ALUZero
            //This is the offset for branching, signextend 64
            NextPC = CurrentPC + SignExtImm64; //got rid of the <<2 and everything worked
        end
        else begin 
            //If neither are true, the next instruction is sequential, so add 4 to the CurrentPC
            NextPC = CurrentPC + 64'd4; 
        end
    end

    endmodule

data/TAMU Classes/Spring 2024/ECEN350/Lab09/DataMemory.v
`timescale 1ns / 1ps

`define SIZE 1024

module DataMemory(ReadData , Address , WriteData , MemoryRead , MemoryWrite , Clock);
   input [63:0]      WriteData;
   input [63:0]      Address;
   input             Clock, MemoryRead, MemoryWrite;
   output reg [63:0] ReadData;

   reg [7:0] 	     memBank [`SIZE-1:0];


   // This task is used to write arbitrary data to the Data Memory by
   // the intialization block.
   task initset;
      input [63:0] addr;
      input [63:0] data;
      begin
	 memBank[addr] =  data[63:56] ; // Big-endian for the win...
	 memBank[addr+1] =  data[55:48];
	 memBank[addr+2] =  data[47:40];
	 memBank[addr+3] =  data[39:32];
	 memBank[addr+4] =  data[31:24];
	 memBank[addr+5] =  data[23:16];
	 memBank[addr+6] =  data[15:8];
	 memBank[addr+7] =  data[7:0];
      end
   endtask

   initial
     begin
        // preseting some data in the data memory used by test #1

        // Address 0x0 gets 0x1
        initset( 64'h0,  64'h1);  //Counter variable
        initset( 64'h8,  64'ha);  //Part of mask
        initset( 64'h10, 64'h5);  //Other part of mask
        initset( 64'h18, 64'h0ffbea7deadbeeff); //big constant
        initset( 64'h20, 64'h0); //clearing space

        // Add any data you need for your tests here.

     end

   // This always block reads the data memory and places a double word
   // on the ReadData bus.
   always @(posedge Clock)
     begin
        if(MemoryRead)
          begin
             ReadData[63:56] <=  memBank[Address];
             ReadData[55:48] <=  memBank[Address+1];
             ReadData[47:40] <=  memBank[Address+2];
             ReadData[39:32] <=  memBank[Address+3];
             ReadData[31:24] <=  memBank[Address+4];
             ReadData[23:16] <=  memBank[Address+5];
             ReadData[15:8] <=  memBank[Address+6];
             ReadData[7:0] <=  memBank[Address+7];
          end
     end

   // This always block takes data from the WriteData bus and writes
   // it into the DataMemory.
   always @(posedge Clock)
     begin
        if(MemoryWrite)
          begin
             memBank[Address] <= #3 WriteData[63:56] ;
             memBank[Address+1] <= #3 WriteData[55:48];
             memBank[Address+2] <= #3 WriteData[47:40];
             memBank[Address+3] <= #3 WriteData[39:32];
             memBank[Address+4] <= #3 WriteData[31:24];
             memBank[Address+5] <= #3 WriteData[23:16];
             memBank[Address+6] <= #3 WriteData[15:8];
             memBank[Address+7] <= #3 WriteData[7:0];
             // Could be useful for debugging:
            $display("Writing Address:%h Data:%h",Address, WriteData);
          end
     end
endmodule

data/TAMU Classes/Spring 2024/ECEN350/Lab09/RegisterFile.v
//`timescale 1ns / 1ps

module RegisterFile( BusA, BusB, BusW, RA, RB, RW, RegWr, Clk );
    // output reg [63:0] BusA;
    // output reg [63:0] BusB; //Make outputs "reg"
    output [63:0] BusA;
    output [63:0] BusB;
    input [63:0] BusW;
    input [4:0] RA;
    input [4:0] RB;
    input [4:0] RW;
    input RegWr;
    input Clk;
    reg[63:0] registers[31:0]; // Change from 32 to 64 bits with registers 32 bits wide

    initial registers[31] = 64'b0;

    // Might not need an always block here
    // always @(posedge Clk) begin
                        // read from the registers with 2-ticks for the delay
                        // The #2 is for the time delay
                        // check that register 31 is incorporated in the read logic
        // BusA <= #2 (RA == 5'b11111) ? 64'b0 : registers[RA];
        // BusB <= #2 (RB == 5'b11111) ? 64'b0 : registers[RB]; //using <= non blocking so it loads all at once
    assign #2 BusA = registers[RA];
    assign #2 BusB = registers[RB];
    // end

    // write to reg on the falling edge of a 3tick clock
    always @(negedge Clk) begin
        if (RegWr && RW != 5'b11111) begin //check if regwr is on and the value in RW is not 32
            registers[RW] <= #3 BusW;
        end
    end

    endmodule

data/TAMU Classes/Spring 2024/ECEN350/Lab09/ALU.v
//`timescale 1ns / 1ps

`define AND   4'b0000
`define OR    4'b0001
`define ADD   4'b0010
`define SUB   4'b0110
`define PassB 4'b0111

module ALU(BusW, BusA, BusB, ALUCtrl, Zero);
    
    output  [63:0] BusW;
    input   [63:0] BusA, BusB;
    input   [3:0] ALUCtrl;
    output  Zero;
    reg     [63:0] BusW;
    
    always @(ALUCtrl or BusA or BusB) begin //go to each case which is specified
        case(ALUCtrl)
            `AND:
                BusW <= BusA & BusB;
            `OR:
                BusW <= BusA | BusB;
            `ADD:
                BusW <= BusA + BusB;
            `SUB:
                BusW <= BusA - BusB;
            `PassB:
                BusW <= BusB;
            endcase
    end
    assign #1 Zero = (BusW == 0) ? 1'b1 : 1'b0;
endmodule

data/TAMU Classes/Spring 2024/ECEN350/Lab09/SignExtender.v
// `timescale 1ns/1ps
// `default_nettype none 

module SignExtender(BusImm, Imm16, Ctrl); 
   output [63:0] BusImm; 
   input [25:0]  Imm16; 
   input [2:0]	 Ctrl; //For MOVZ
   reg[63:0] result; //We had to add this in to store the result

   always @(*) begin
	      case(Ctrl) //Cleaned up by removing begin and end clauses and simplifying down to one line of code per case
	   3'b000: //I-type
           begin
            result = {{52'b0}, Imm16[21:10]}; // Sign-extend from bit 21
           end
	   3'b001: //D-type data processing 
           begin
	      result = {{55{Imm16[20]}}, Imm16[20:12]};
           end
	   3'b010: //B-type
           begin
	      result = {{36{Imm16[25]}}, Imm16[25:0], 2'b00};
           end
	   3'b011: //BZ-type
           begin
	      result = {{43{Imm16[23]}}, Imm16[23:5], 2'b00};
           end
         3'b100: begin
            case (Imm16[22:21])
                  3'b00: begin
                        result = {{48{1'b0}}, Imm16[20:5]};
                  end
                  2'b01: begin
                        result = {{32{1'b0}}, Imm16[20:5],{16{1'b0}}};
                  end
                  2'b10: begin
                        result = {{16{1'b0}}, Imm16[20:5],{32{1'b0}}};
                  end
                  2'b11: begin
                        result = {Imm16[20:5], {48{1'b0}}};
                  end
            endcase
         end
      endcase
      end
      assign BusImm = result;
endmodule

data/TAMU Classes/Spring 2024/ECEN350/Lab09/SingleCycleControl.v
//`timescale 1ns / 1ps


`define OPCODE_ANDREG 11'b?0001010???
`define OPCODE_ORRREG 11'b?0101010???
`define OPCODE_ADDREG 11'b?0?01011???
`define OPCODE_SUBREG 11'b?1?01011???

`define OPCODE_ADDIMM 11'b?0?10001???
`define OPCODE_SUBIMM 11'b?1?10001???

`define OPCODE_MOVZ   11'b110100101?? //correct

`define OPCODE_B      11'b?00101????? //Done
`define OPCODE_CBZ    11'b?011010???? //Done

`define OPCODE_LDUR   11'b??111000010 //Done
`define OPCODE_STUR   11'b??111000000 //Done

module control(
	       output reg 	reg2loc,
	       output reg 	alusrc,
	       output reg 	mem2reg,
	       output reg 	regwrite,
	       output reg 	memread,
	       output reg 	memwrite,
	       output reg 	branch,
	       output reg 	uncond_branch,
	       output reg [3:0] aluop,
	       output reg [2:0] signop,
	       input [10:0] 	opcode
	       );

   always @(*)
     begin
	casez (opcode)

          /* Add cases here for each instruction your processor supports */

          `OPCODE_LDUR:
            begin
               reg2loc       = 1'bx;
               alusrc        = 1'b1;
               mem2reg       = 1'b1;
               regwrite      = 1'b1;
               memread       = 1'b1;
               memwrite      = 1'b0;
               branch        = 1'b0;
               uncond_branch = 1'b0;
               aluop         = 4'b0010;
              //  signop        = 2'b01;
               signop        = 3'b001;
            end

          `OPCODE_STUR:
            begin
               reg2loc       = 1'b1;
               alusrc        = 1'b1;
               mem2reg       = 1'b0;
               regwrite      = 1'b0;
               memread       = 1'b0;
               memwrite      = 1'b1;
               branch        = 1'b0;
               uncond_branch = 1'b0;
               aluop         = 4'b0010;
              //  signop        = 2'b01; 
               signop        = 3'b001;  
            end

          `OPCODE_ADDREG:
            begin
               reg2loc       = 1'b0;
               alusrc        = 1'b0;
               mem2reg       = 1'b0;
               regwrite      = 1'b1;
               memread       = 1'b0;
               memwrite      = 1'b0;
               branch        = 1'b0;
               uncond_branch = 1'b0;
               aluop         = 4'b0010;
              //  signop        = 2'bxx;
               signop        = 3'bxxx;
            end

          `OPCODE_SUBREG:
            begin
               reg2loc       = 1'b0;
               alusrc        = 1'b0;
               mem2reg       = 1'b0;
               regwrite      = 1'b1;
               memread       = 1'b0;
               memwrite      = 1'b0;
               branch        = 1'b0;
               uncond_branch = 1'b0;
               aluop         = 4'b0110;
              //  signop        = 2'bxx;
               signop        = 3'bxxx;
            end

          `OPCODE_ANDREG:
            begin
               reg2loc       = 1'b0;
               alusrc        = 1'b0;
               mem2reg       = 1'b0;
               regwrite      = 1'b1;
               memread       = 1'b0;
               memwrite      = 1'b0;
               branch        = 1'b0;
               uncond_branch = 1'b0;
               aluop         = 4'b0000;
              //  signop        = 2'bxx;
               signop        = 3'bxxx;               
            end

          `OPCODE_ORRREG:
            begin
               reg2loc       = 1'b0;
               alusrc        = 1'b0;
               mem2reg       = 1'b0;
               regwrite      = 1'b1;
               memread       = 1'b0;
               memwrite      = 1'b0;
               branch        = 1'b0;
               uncond_branch = 1'b0;
               aluop         = 4'b0001;
              //  signop        = 2'bxx;
               signop        = 3'bxxx;               
            end

          `OPCODE_CBZ:
            begin
               reg2loc       = 1'b1;
               alusrc        = 1'b0;
               mem2reg       = 1'bx;
               regwrite      = 1'b0;
               memread       = 1'b0;
               memwrite      = 1'b0;
               branch        = 1'b1;
               uncond_branch = 1'b0;
               aluop         = 4'b0111;
              //  signop        = 2'b11; 
               signop        = 3'b011;
            end

          `OPCODE_B:
            begin
               reg2loc       = 1'bx;
               alusrc        = 1'bx;
               mem2reg       = 1'bx;
               regwrite      = 1'b0;
               memread       = 1'b0;
               memwrite      = 1'b0;
               branch        = 1'bx;
               uncond_branch = 1'b1;
               aluop         = 4'bxxxx;
               //signop        = 2'b10;
               signop        = 3'b010;
            end
            
            // MOVZ
            `OPCODE_MOVZ:
            begin
                reg2loc       = 1'b0;
                alusrc        = 1'b1; 
                mem2reg       = 1'b0;
                regwrite      = 1'b1;
                memread       = 1'b0;
                memwrite      = 1'b0;
                branch        = 1'b0;
                uncond_branch = 1'b0;
                aluop         = 4'b0111;
                signop        = 3'b100; 
            end

          `OPCODE_ADDIMM:
            begin
              reg2loc       = 1'bx; 
              alusrc        = 1'b1;  
              mem2reg       = 1'b0;
              regwrite      = 1'b1;
              memread       = 1'b0;
              memwrite      = 1'b0;
              branch        = 1'b0;
              uncond_branch = 1'b0;
              aluop         = 4'b0010; 
              // signop        = 2'b00;  
              signop        = 3'b000;
            end

          `OPCODE_SUBIMM:
            begin
               reg2loc       = 1'bx;
               alusrc        = 1'b1;
               mem2reg       = 1'b0;
               regwrite      = 1'b1;
               memread       = 1'b0;
               memwrite      = 1'b0;
               branch        = 1'b0;
               uncond_branch = 1'b0;
               aluop         = 4'b0110;
              //  signop        = 2'b00;
               signop        = 3'b000;
            end

          default:
            begin
               reg2loc       = 1'bx;
               alusrc        = 1'bx;
               mem2reg       = 1'bx;
               regwrite      = 1'b0;
               memread       = 1'b0;
               memwrite      = 1'b0;
               branch        = 1'b0;
               uncond_branch = 1'b0;
               aluop         = 4'bxxxx;
              //  signop        = 2'bxx;
               signop        = 3'bxxx;
            end
	endcase
     end

endmodule

data/TAMU Classes/Spring 2024/ECEN350/Lab09/InstructionMemory.v
`timescale 1ns / 1ps
/*
 * Module: InstructionMemory
 *
 * Implements read-only instruction memory
 * 
 */
module InstructionMemory(Data, Address);
   parameter T_rd = 20;
   parameter MemSize = 40;
   
   output [31:0] Data;
   input [63:0]  Address;
   reg [31:0] 	 Data;
   
   /*
    * ECEN 350 Processor Test Functions
    * Texas A&M University
    */
   
   always @ (Address) begin

      case(Address)

	// * Test Program 1:
	// Program loads constants from the data memory. Uses these constants to test
	// the following instructions: LDUR, ORR, AND, CBZ, ADD, SUB, STUR and B.
	
	// Assembly code for test:
	
	// 0: LDUR X9, [XZR, 0x0]    //Load 1 into x9
	// 4: LDUR X10, [XZR, 0x8]   //Load a into x10
	// 8: LDUR X11, [XZR, 0x10]  //Load 5 into x11
	// C: LDUR X12, [XZR, 0x18]  //Load big constant into x12
	// 10: LDUR X13, [XZR, 0x20]  //load a 0 into X13
	
	// 14: ORR X10, X10, X11  //Create mask of 0xf
	// 18: AND X12, X12, X10  //Mask off low order bits of big constant
	
	// loop:
	// 1C: CBZ X12, end  //while X12 is not 0
	// 20: ADD X13, X13, X9  //Increment counter in X13
	// 24: SUB X12, X12, X9  //Decrement remainder of big constant in X12
	// 28: B loop  //Repeat till X12 is 0
	// 2C: STUR X13, [XZR, 0x20];  //store back the counter value into the memory location 0x20
	
	
	// 0: LDUR X9, [XZR, 0x0]    //Load 1 into x9
	63'h000: Data = 32'hF84003E9;
	63'h004: Data = 32'hF84083EA;
	63'h008: Data = 32'hF84103EB;		//HF84 == LDUR //hAA ==ORR
	63'h00c: Data = 32'hF84183EC;
	63'h010: Data = 32'hF84203ED;
	63'h014: Data = 32'hAA0B014A;
	63'h018: Data = 32'h8A0A018C;
	63'h01c: Data = 32'hB400008C;
	63'h020: Data = 32'h8B0901AD;
	63'h024: Data = 32'hCB09018C;
	63'h028: Data = 32'h17FFFFFD;
	63'h02c: Data = 32'hF80203ED;
	63'h030: Data = 32'hF84203ED;  //One last load to place stored value on memdbus for test checking.

	/* Add code for your tests here */
	//34: MOVZ X9, #0x1234, LSL #48
	//38: ADD X9, X9, #0x5678
	//3c: ADD X9, X9, #0xabc0000
	//40: ADD X9, X9, 0xdef00000000
	//Store value
	//44: ADDI X1, XZR, #0x28
	//48: STUR X9, [X1]
	//4c: LDUR X10, [X1]

	// 63'h034: Data = 32'h8A0A018C;
	// 63'h038: Data = 32'hB400008C;
	// 63'h03c: Data = 32'h8B0901AD;
	// 63'h040: Data = 32'hCB09018C;
	// 63'h044: Data = 32'h17FFFFFD;
	// 63'h048: Data = 32'hF80203ED;
	// 63'h04c: Data = 32'hF84203ED;

	63'h034: Data = 32'hD2E24680;
	63'h038: Data = 32'hD2CACF01; // Add immediate (shifted left by 12 bits, #0x5678)
	63'h03c: Data = 32'h8B010009; // Add immediate (shifted left by 12 bits, #0xABC0)
	63'h040: Data = 32'hD2B35780; // Add immediate (shifted left by 12 bits, #0xDEF0)
	63'h044: Data = 32'hD29BDE01; // Add immediate to XZR
	63'h048: Data = 32'h8B010003; // Store X9 at address in X1 + offset 0
	63'h04c: Data = 32'h8B030129; // Load into X10 from
	63'h050: Data = 32'hF80283E9; // Load into X10 from
	63'h054: Data = 32'hF84283EA; // Load into X10 from

	
	default: Data = 32'hXXXXXXXX;
      endcase
   end
endmodule

data/TAMU Classes/Spring 2024/ECEN350/Lab09/SingleCycleProc.v
`timescale 1ns / 1ps

module singlecycle(
		   input 	     resetl,
		   input [63:0]      startpc,
		   output reg [63:0] currentpc,
		   output [63:0]     MemtoRegOut,  // this should be
						   // attached to the
						   // output of the
						   // MemtoReg Mux
		   input 	     CLK
		   );

   // Next PC connections
   wire [63:0] 			     nextpc;       // The next PC, to be updated on clock cycle

   // Instruction Memory connections
   wire [31:0] 			     instruction;  // The current instruction

   // Parts of instruction
   wire [4:0] 			     rd;            // The destination register
   wire [4:0] 			     rm;            // Operand 1
   wire [4:0] 			     rn;            // Operand 2
   wire [10:0] 			     opcode;

   // Control wires
   wire 			     reg2loc;
   wire 			     alusrc;
   wire 			     mem2reg;
   wire 			     regwrite;
   wire 			     memread;
   wire 			     memwrite;
   wire 			     branch;
   wire 			     uncond_branch;
   wire [3:0] 			     aluctrl;
   wire [2:0] 			     signop;

   // Register file connections
   wire [63:0] 			     regoutA;     // Output A
   wire [63:0] 			     regoutB;     // Output B
   wire [63:0]           datamux;

   // ALU connections
   wire [63:0] 			     aluout;
   wire 			           zero;
   wire [63:0]           alumux;

   // Sign Extender connections
   wire [63:0] 			     extimm;

   // PC update logic
   always @(negedge CLK)
     begin
        if (resetl)
          currentpc <= #3 nextpc;
        else
          currentpc <= #3 startpc;
     end

   // Parts of instruction
   assign rd = instruction[4:0];
   assign rm = instruction[9:5];
   assign rn = reg2loc ? instruction[4:0] : instruction[20:16];
   assign opcode = instruction[31:21];

   InstructionMemory imem(
			  .Data(instruction),
			  .Address(currentpc)
			  );

   control control(
		   .reg2loc(reg2loc),
		   .alusrc(alusrc),
		   .mem2reg(mem2reg),
		   .regwrite(regwrite),
		   .memread(memread),
		   .memwrite(memwrite),
		   .branch(branch),
		   .uncond_branch(uncond_branch),
		   .aluop(aluctrl),
		   .signop(signop),
		   .opcode(opcode)
		  );

    SignExtender SignExtender(
        .BusImm(extimm), 
        .Imm16(instruction[25:0]),
        .Ctrl(signop)    
      );

   assign alumux = alusrc ? extimm : regoutB;
    ALU ALU(
        .BusW(aluout), //Output
        .BusA(regoutA), //Input
        .BusB(alumux), //Input
        .ALUCtrl(aluctrl), 
        .Zero(zero)
      );

    RegisterFile RegisterFile (
      .BusA(regoutA),
      .BusB(regoutB),
      .BusW(datamux),
      .RA(rm),
      .RB(rn),
      .RW(rd),
      .RegWr(regwrite),
      .Clk(CLK)
      );

    assign datamux = mem2reg ? MemtoRegOut : aluout;
    DataMemory dataMemory(
      .ReadData(MemtoRegOut),
      .Address(aluout),
      .WriteData(regoutB),
      .MemoryRead(memread),
      .MemoryWrite(memwrite),
      .Clock(CLK)
      );

    NextPClogic NextPCLogic(
      .NextPC(nextpc),
      .CurrentPC(currentpc),
      .SignExtImm64(extimm),  // Assuming sign extended immediate is used for address calculation
      .Branch(branch),
      .ALUZero(zero),
      .Uncondbranch(uncond_branch)
      );

   /*
    * Connect the remaining datapath elements below.
    * Do not forget any additional multiplexers that may be required.
    */

endmodule

data/TAMU Classes/Spring 2024/ECEN350/Lab09/SingleCycleProcTest.v
`timescale 1ns / 1ps

`define STRLEN 32
`define HalfClockPeriod 60
`define ClockPeriod `HalfClockPeriod * 2

module SingleCycleProcTest_v;

   initial
     begin
        $dumpfile("singlecycle.vcd");
        $dumpvars;
     end

   // These tasks are used to check if a given test has passed and
   // confirm that all tests passed.
   task passTest;
      input [63:0] actualOut, expectedOut;
      input [`STRLEN*8:0] testType;
      inout [7:0] 	  passed;

      if(actualOut == expectedOut) begin $display ("%s passed", testType); passed = passed + 1; end
      else $display ("%s failed: 0x%x should be 0x%x", testType, actualOut, expectedOut);
   endtask

   task allPassed;
      input [7:0] passed;
      input [7:0] numTests;

      if(passed == numTests) $display ("All tests passed");
      else $display("Some tests failed: %d of %d passed", passed, numTests);
   endtask

   // Inputs
   reg 		  CLK;
   reg 		  Reset_L;
   reg [63:0] 	  startPC;
   reg [7:0] 	  passed;
   reg [15:0] 	  watchdog;

   // Outputs
   wire [63:0] 	  MemtoRegOut;
   wire [63:0] 	  currentPC;

   // Instantiate the Unit Under Test (UUT)
   singlecycle uut (
		    .CLK(CLK),
		    .resetl(Reset_L),
		    .startpc(startPC),
		    .currentpc(currentPC),
		    .MemtoRegOut(MemtoRegOut)
		    );

   initial begin
      // Initialize Inputs
      Reset_L = 1;
      startPC = 0;
      passed = 0;

      // Initialize Watchdog timer
      watchdog = 0;

      // Wait for global reset
      #(1 * `ClockPeriod);

      // Program 1
      #1
        Reset_L = 0; startPC = 0;
      @(posedge CLK);
      @(negedge CLK);
      @(posedge CLK);
      Reset_L = 1;

      // ***********************************************************
      // This while loop will continue cycling the processor until the
      // PC reaches the final instruction in the first test.  If the
      // program forms an infinite loop, never reaching the end, the
      // watchdog timer will kick in and kill simulation after 64K
      // cycles.
      // ***********************************************************

      while (currentPC < 64'h30)
        begin
	   @(posedge CLK);
	   @(negedge CLK);
           $display("CurrentPC:%h",currentPC);
        end
      passTest(MemtoRegOut, 64'hF, "Results of Program 1", passed);
      // passTest(currentPC, 64'h30, "Results of Program 1", passed);


      // ***********************************************************
      // Add your new tests here
      while (currentPC < 64'h54)
        begin
	   @(posedge CLK);
	   @(negedge CLK);
           $display("CurrentPC:%h",currentPC);
        end
      passTest(MemtoRegOut, 64'h123456789abcdef0, "Results of Program 1", passed);
      // ***********************************************************

      // Done
      allPassed(passed, 2);   // Be sure to change the one to match
      // the number of tests you add.
      $finish;
   end

   // Initialize the clock to be 0
   initial begin
      CLK = 0;
   end

   // The following is correct if clock starts at LOW level at StartTime //
   always begin
      #`HalfClockPeriod CLK = ~CLK;
      #`HalfClockPeriod CLK = ~CLK;
      watchdog = watchdog +1;
   end

   // Kill the simulation if the watchdog hits 64K cycles
   always @*
     if (watchdog == 16'hFF)
       begin
          $display("Watchdog Timer Expired.");
          $finish;
       end

endmodule

data/TAMU Classes/Spring 2024/ECEN350/Lab09/singlecycle.vcd
$date
	Mon Apr 22 16:01:31 2024
$end
$version
	Icarus Verilog
$end
$timescale
	1ps
$end
$scope module SingleCycleProcTest_v $end
$var wire 64 ! currentPC [63:0] $end
$var wire 64 " MemtoRegOut [63:0] $end
$var reg 1 # CLK $end
$var reg 1 $ Reset_L $end
$var reg 8 % passed [7:0] $end
$var reg 64 & startPC [63:0] $end
$var reg 16 ' watchdog [15:0] $end
$scope module uut $end
$var wire 1 # CLK $end
$var wire 1 $ resetl $end
$var wire 64 ( startpc [63:0] $end
$var wire 1 ) zero $end
$var wire 1 * uncond_branch $end
$var wire 3 + signop [2:0] $end
$var wire 5 , rn [4:0] $end
$var wire 5 - rm [4:0] $end
$var wire 1 . regwrite $end
$var wire 64 / regoutB [63:0] $end
$var wire 64 0 regoutA [63:0] $end
$var wire 1 1 reg2loc $end
$var wire 5 2 rd [4:0] $end
$var wire 11 3 opcode [10:0] $end
$var wire 64 4 nextpc [63:0] $end
$var wire 1 5 memwrite $end
$var wire 1 6 memread $end
$var wire 1 7 mem2reg $end
$var wire 32 8 instruction [31:0] $end
$var wire 64 9 extimm [63:0] $end
$var wire 64 : datamux [63:0] $end
$var wire 1 ; branch $end
$var wire 1 < alusrc $end
$var wire 64 = aluout [63:0] $end
$var wire 64 > alumux [63:0] $end
$var wire 4 ? aluctrl [3:0] $end
$var wire 64 @ MemtoRegOut [63:0] $end
$var reg 64 A currentpc [63:0] $end
$scope module ALU $end
$var wire 64 B BusB [63:0] $end
$var wire 1 ) Zero $end
$var wire 64 C BusA [63:0] $end
$var wire 4 D ALUCtrl [3:0] $end
$var reg 64 E BusW [63:0] $end
$upscope $end
$scope module NextPCLogic $end
$var wire 1 ) ALUZero $end
$var wire 64 F CurrentPC [63:0] $end
$var wire 1 * Uncondbranch $end
$var wire 64 G SignExtImm64 [63:0] $end
$var wire 1 ; Branch $end
$var reg 64 H NextPC [63:0] $end
$upscope $end
$scope module RegisterFile $end
$var wire 64 I BusA [63:0] $end
$var wire 64 J BusB [63:0] $end
$var wire 64 K BusW [63:0] $end
$var wire 1 # Clk $end
$var wire 5 L RA [4:0] $end
$var wire 5 M RB [4:0] $end
$var wire 5 N RW [4:0] $end
$var wire 1 . RegWr $end
$upscope $end
$scope module SignExtender $end
$var wire 26 O Imm16 [25:0] $end
$var wire 3 P Ctrl [2:0] $end
$var wire 64 Q BusImm [63:0] $end
$var reg 64 R result [63:0] $end
$upscope $end
$scope module control $end
$var wire 11 S opcode [10:0] $end
$var reg 4 T aluop [3:0] $end
$var reg 1 < alusrc $end
$var reg 1 ; branch $end
$var reg 1 7 mem2reg $end
$var reg 1 6 memread $end
$var reg 1 5 memwrite $end
$var reg 1 1 reg2loc $end
$var reg 1 . regwrite $end
$var reg 3 U signop [2:0] $end
$var reg 1 * uncond_branch $end
$upscope $end
$scope module dataMemory $end
$var wire 64 V Address [63:0] $end
$var wire 1 # Clock $end
$var wire 1 6 MemoryRead $end
$var wire 1 5 MemoryWrite $end
$var wire 64 W WriteData [63:0] $end
$var reg 64 X ReadData [63:0] $end
$scope task initset $end
$var reg 64 Y addr [63:0] $end
$var reg 64 Z data [63:0] $end
$upscope $end
$upscope $end
$scope module imem $end
$var wire 64 [ Address [63:0] $end
$var parameter 32 \ MemSize $end
$var parameter 32 ] T_rd $end
$var reg 32 ^ Data [31:0] $end
$upscope $end
$upscope $end
$scope task allPassed $end
$var reg 8 _ numTests [7:0] $end
$var reg 8 ` passed [7:0] $end
$upscope $end
$scope task passTest $end
$var reg 64 a actualOut [63:0] $end
$var reg 64 b expectedOut [63:0] $end
$var reg 8 c passed [7:0] $end
$var reg 257 d testType [256:0] $end
$upscope $end
$upscope $end
$enddefinitions $end
$comment Show the parameter values. $end
$dumpall
b10100 ]
b101000 \
$end
#0
$dumpvars
bx d
bx c
bx b
bx a
bx `
bx _
bx ^
bx [
b0 Z
b100000 Y
bx X
bx W
bx V
bx U
bx T
bx S
bx R
bx Q
bx P
bx O
bx N
bx M
bx L
bx K
bx J
bx I
bx H
bx G
bx F
bx E
bx D
bx C
bx B
bx A
bx @
bx ?
bx >
bx =
x<
x;
bx :
bx 9
bx 8
x7
x6
x5
bx 4
bx 3
bx 2
x1
bx 0
bx /
x.
bx -
bx ,
bx +
x*
x)
b0 (
b0 '
b0 &
b0 %
1$
0#
bx "
bx !
$end
#60000
1#
#120000
b1 '
0#
#121000
0$
#180000
1#
#240000
b10 '
0#
#243000
b0 >
b0 B
b0 9
b0 G
b0 Q
b0 R
b1 +
b1 P
b1 U
b10 ?
b10 D
b10 T
0*
0;
05
16
1.
17
1<
b0x00x ,
b0x00x M
b10000000000001111101001 O
b11111000010 3
b11111000010 S
b11111 -
b11111 L
b1001 2
b1001 N
b100 4
b100 H
b11111000010000000000001111101001 8
b11111000010000000000001111101001 ^
b0 !
b0 A
b0 F
b0 [
#245000
b0 =
b0 E
b0 V
b0 0
b0 C
b0 I
#246000
1)
#300000
b1 :
b1 K
b1 "
b1 @
b1 X
1$
1#
#360000
b11 '
0#
#363000
b1000 =
b1000 E
b1000 V
b1000 >
b1000 B
b1000 9
b1000 G
b1000 Q
b1000 R
b0x0x0 ,
b0x0x0 M
b10000001000001111101010 O
b1010 2
b1010 N
b1000 4
b1000 H
b11111000010000001000001111101010 8
b11111000010000001000001111101010 ^
b100 !
b100 A
b100 F
b100 [
#364000
0)
#420000
b1010 :
b1010 K
b1010 "
b1010 @
b1010 X
1#
#480000
b100 '
0#
#483000
b10000 =
b10000 E
b10000 V
b10000 >
b10000 B
b10000 9
b10000 G
b10000 Q
b10000 R
b0x0x1 ,
b0x0x1 M
b10000010000001111101011 O
b1011 2
b1011 N
b1100 4
b1100 H
b11111000010000010000001111101011 8
b11111000010000010000001111101011 ^
b1000 !
b1000 A
b1000 F
b1000 [
#540000
b101 :
b101 K
b101 "
b101 @
b101 X
1#
#600000
b101 '
0#
#603000
b11000 =
b11000 E
b11000 V
b11000 >
b11000 B
b11000 9
b11000 G
b11000 Q
b11000 R
b0xx0x ,
b0xx0x M
b10000011000001111101100 O
b1100 2
b1100 N
b10000 4
b10000 H
b11111000010000011000001111101100 8
b11111000010000011000001111101100 ^
b1100 !
b1100 A
b1100 F
b1100 [
#660000
b111111111011111010100111110111101010110110111110111011111111 :
b111111111011111010100111110111101010110110111110111011111111 K
b111111111011111010100111110111101010110110111110111011111111 "
b111111111011111010100111110111101010110110111110111011111111 @
b111111111011111010100111110111101010110110111110111011111111 X
1#
#720000
b110 '
0#
#723000
b100000 =
b100000 E
b100000 V
b100000 >
b100000 B
b100000 9
b100000 G
b100000 Q
b100000 R
b0xxxx ,
b0xxxx M
b10000100000001111101101 O
b1101 2
b1101 N
b10100 4
b10100 H
b11111000010000100000001111101101 8
b11111000010000100000001111101101 ^
b10000 !
b10000 A
b10000 F
b10000 [
#780000
b0 :
b0 K
b0 "
b0 @
b0 X
1#
#840000
b111 '
0#
#843000
bx =
bx E
bx V
bx :
bx K
bx >
bx B
bx +
bx P
bx U
b1 ?
b1 D
b1 T
06
07
0<
01
b1011 ,
b1011 M
b10000010110000000101001010 O
b10101010000 3
b10101010000 S
b1010 -
b1010 L
b1010 2
b1010 N
b11000 4
b11000 H
b10101010000010110000000101001010 8
b10101010000010110000000101001010 ^
b10100 !
b10100 A
b10100 F
b10100 [
#844000
x)
#845000
b1111 :
b1111 K
b1111 =
b1111 E
b1111 V
b101 >
b101 B
b101 /
b101 J
b101 W
b1010 0
b1010 C
b1010 I
#846000
0)
#900000
1#
#960000
b1000 '
0#
#963000
b0 :
b0 K
b0 =
b0 E
b0 V
b0 ?
b0 D
b0 T
b1010 ,
b1010 M
b10000010100000000110001100 O
b10001010000 3
b10001010000 S
b1100 -
b1100 L
b1100 2
b1100 N
b11100 4
b11100 H
b10001010000010100000000110001100 8
b10001010000010100000000110001100 ^
b11000 !
b11000 A
b11000 F
b11000 [
#964000
1)
#965000
b1111 :
b1111 K
b1111 =
b1111 E
b1111 V
b1111 >
b1111 B
b1111 /
b1111 J
b1111 W
b111111111011111010100111110111101010110110111110111011111111 0
b111111111011111010100111110111101010110110111110111011111111 C
b111111111011111010100111110111101010110110111110111011111111 I
#966000
0)
#1020000
1#
#1080000
b1001 '
0#
#1083000
b0xxxx :
b0xxxx K
b10000 9
b10000 G
b10000 Q
b10000 R
b11 +
b11 P
b11 U
b111 ?
b111 D
b111 T
1;
0.
x7
11
b1100 ,
b1100 M
b10001100 O
b10110100000 3
b10110100000 S
b100 -
b100 L
b100000 4
b100000 H
b10110100000000000000000010001100 8
b10110100000000000000000010001100 ^
b11100 !
b11100 A
b11100 F
b11100 [
#1085000
bx 0
bx C
bx I
#1140000
1#
#1200000
b1010 '
0#
